streamlit_mnist_canvas/__init__.py
streamlit_mnist_canvas/frontend/index.html
streamlit_mnist_canvas/frontend/main.js
streamlit_mnist_canvas/frontend/streamlit-component-lib.js
streamlit_mnist_canvas/frontend/style.css
streamlit_mnist_canvas-0.1.1.dist-info/LICENSE
streamlit_mnist_canvas-0.1.1.dist-info/METADATA
streamlit_mnist_canvas-0.1.1.dist-info/WHEEL
streamlit_mnist_canvas-0.1.1.dist-info/top_level.txt
streamlit_mnist_canvas-0.1.1.dist-info/RECORD
