Metadata-Version: 2.1
Name: streamlit-mnist-canvas
Version: 0.1.1
Summary: A Streamlit component tailored for handwriting digit recognition using the MNIST dataset. This component allows users to draw digits on a canvas, facilitating integration with various machine learning models for digit recognition. It's ideal for educational, development, and testing purposes within Streamlit applications.
Home-page: https://github.com/Gohei/streamlit_mnist_canvas
Author: Gohei Kusumi
Author-email: gohei.kusumi@gmail.com
Classifier: Programming Language :: Python :: 3
Classifier: License :: OSI Approved :: MIT License
Classifier: Operating System :: OS Independent
Requires-Python: >=3.9
License-File: LICENSE
